NJmatML/__init__.py
NJmatML/dataML.py
NJmatML-0.0.11.dist-info/METADATA
NJmatML-0.0.11.dist-info/WHEEL
NJmatML-0.0.11.dist-info/top_level.txt
NJmatML-0.0.11.dist-info/RECORD
