Metadata-Version: 2.1
Name: NJmatML
Version: 0.0.11
Summary: Automates data-driven machine learning for materials science via NJmatML (材料数据可视化、机器学习建模与预测)
Home-page: UNKNOWN
Author: Lei_Zhang
Author-email: ervin42772@gmail.com
License: UNKNOWN
Platform: UNKNOWN
Classifier: Programming Language :: Python :: 3.7
Classifier: License :: OSI Approved :: MIT License
Classifier: Operating System :: OS Independent
